gantt.py
minimal_gantt-0.2.2.data/scripts/csv2gantt
minimal_gantt-0.2.2.dist-info/DESCRIPTION.rst
minimal_gantt-0.2.2.dist-info/METADATA
minimal_gantt-0.2.2.dist-info/RECORD
minimal_gantt-0.2.2.dist-info/WHEEL
minimal_gantt-0.2.2.dist-info/metadata.json
minimal_gantt-0.2.2.dist-info/top_level.txt
