Metadata-Version: 2.0
Name: minimal-gantt
Version: 0.2.2
Summary: A minimal Gantt chart generator
Home-page: UNKNOWN
Author: Olav Vahtras
Author-email: olav.vahtras@gmail.com
License: MIT
Platform: UNKNOWN
Requires-Dist: pandas
Requires-Dist: seaborn
